supplychainmodelhelper/__init__.py
supplychainmodelhelper/datahandling.py
supplychainmodelhelper/drawer.py
supplychainmodelhelper/graphoperations.py
supplychainmodelhelper/graphoperationsCLASS.py
supplychainmodelhelper/mds.py
supplychainmodelhelper/playground.py
tests/__init__.py
tests/test_dh.py
tests/test_go.py
tests/test_mds.py
supplychainmodelhelper-0.2.7.dist-info/METADATA
supplychainmodelhelper-0.2.7.dist-info/WHEEL
supplychainmodelhelper-0.2.7.dist-info/top_level.txt
supplychainmodelhelper-0.2.7.dist-info/RECORD
