Metadata-Version: 2.1
Name: supplychainmodelhelper
Version: 0.2.7
Summary: A package to help with your supply chain model
Home-page: https://gitlab.com/DjMaFu/supplychainmodulator
Author: Marcel Fuhrmann
Author-email: dr.marcel.fuhrmann@gmail.com
License: UNKNOWN
Platform: UNKNOWN
Classifier: Programming Language :: Python :: 3.9
Classifier: License :: OSI Approved :: GNU General Public License v3 (GPLv3)
Requires-Dist: wheel (>=0.33.1)
Requires-Dist: networkx (>=2.5)
Requires-Dist: h5py (>=3.2.1)
Requires-Dist: numpy (>=1.21.0)
Requires-Dist: twine (>=3.3.0)
Requires-Dist: pandas (>=1.2.3)
Requires-Dist: ipfn (>=1.4.1)
Requires-Dist: scipy (>=1.7.0)
Requires-Dist: matplotlib (>=3.4.3)
